{
  "_generic": {
    "defaultPackage": "criterion",
    "location": "",
    "packages": {
      "criterion": "0.4.0"
    },
    "sourcesAggregatedHash": null,
    "subsystem": "rust"
  },
  "_subsystem": {
    "gitSources": [],
    "meta": {
      "criterion": {
        "0.4.0": {
          "description": "Statistics-driven micro-benchmarking library", "homepage": "https://bheisler.github.io/criterion.rs/book/index.html", "license": []
        }
      }
    },
    "relPathReplacements": {
      "criterion": {
        "0.4.0": {}
      }
    }
  },
  "cyclicDependencies": {},
  "dependencies": {
    "approx": {
      "0.5.1": [
        [ "num-traits", "0.2.15" ]
      ]
    },
    "async-channel": {
      "1.8.0": [
        [ "concurrent-queue", "2.1.0" ],
        [ "event-listener", "2.5.3" ],
        [ "futures-core", "0.3.27" ]
      ]
    },
    "async-executor": {
      "1.5.0": [
        [ "async-lock", "2.7.0" ],
        [ "async-task", "4.4.0" ],
        [ "concurrent-queue", "2.1.0" ],
        [ "fastrand", "1.9.0" ],
        [ "futures-lite", "1.12.0" ],
        [ "slab", "0.4.8" ]
      ]
    },
    "async-fs": {
      "1.6.0": [
        [ "async-lock", "2.7.0" ],
        [ "autocfg", "1.1.0" ],
        [ "blocking", "1.3.0" ],
        [ "futures-lite", "1.12.0" ]
      ]
    },
    "async-global-executor": {
      "2.3.1": [
        [ "async-channel", "1.8.0" ],
        [ "async-executor", "1.5.0" ],
        [ "async-io", "1.13.0" ],
        [ "async-lock", "2.7.0" ],
        [ "blocking", "1.3.0" ],
        [ "futures-lite", "1.12.0" ],
        [ "once_cell", "1.17.1" ]
      ]
    },
    "async-io": {
      "1.13.0": [
        [ "async-lock", "2.7.0" ],
        [ "autocfg", "1.1.0" ],
        [ "cfg-if", "1.0.0" ],
        [ "concurrent-queue", "2.1.0" ],
        [ "futures-lite", "1.12.0" ],
        [ "log", "0.4.17" ],
        [ "parking", "2.0.0" ],
        [ "polling", "2.6.0" ],
        [ "rustix", "0.37.4" ],
        [ "slab", "0.4.8" ],
        [ "socket2", "0.4.9" ],
        [ "waker-fn", "1.1.0" ]
      ]
    },
    "async-lock": {
      "2.7.0": [
        [ "event-listener", "2.5.3" ]
      ]
    },
    "async-net": {
      "1.7.0": [
        [ "async-io", "1.13.0" ],
        [ "autocfg", "1.1.0" ],
        [ "blocking", "1.3.0" ],
        [ "futures-lite", "1.12.0" ]
      ]
    },
    "async-process": {
      "1.6.0": [
        [ "async-io", "1.13.0" ],
        [ "async-lock", "2.7.0" ],
        [ "autocfg", "1.1.0" ],
        [ "blocking", "1.3.0" ],
        [ "cfg-if", "1.0.0" ],
        [ "event-listener", "2.5.3" ],
        [ "futures-lite", "1.12.0" ],
        [ "libc", "0.2.140" ],
        [ "signal-hook", "0.3.15" ],
        [ "windows-sys", "0.42.0" ]
      ]
    },
    "async-std": {
      "1.12.0": [
        [ "async-channel", "1.8.0" ],
        [ "async-global-executor", "2.3.1" ],
        [ "async-io", "1.13.0" ],
        [ "async-lock", "2.7.0" ],
        [ "crossbeam-utils", "0.8.15" ],
        [ "futures-channel", "0.3.27" ],
        [ "futures-core", "0.3.27" ],
        [ "futures-io", "0.3.27" ],
        [ "futures-lite", "1.12.0" ],
        [ "gloo-timers", "0.2.6" ],
        [ "kv-log-macro", "1.0.7" ],
        [ "log", "0.4.17" ],
        [ "memchr", "2.5.0" ],
        [ "once_cell", "1.17.1" ],
        [ "pin-project-lite", "0.2.9" ],
        [ "pin-utils", "0.1.0" ],
        [ "slab", "0.4.8" ],
        [ "wasm-bindgen-futures", "0.4.34" ]
      ]
    },
    "atty": {
      "0.2.14": [
        [ "hermit-abi", "0.1.19" ],
        [ "libc", "0.2.140" ],
        [ "winapi", "0.3.9" ]
      ]
    },
    "blocking": {
      "1.3.0": [
        [ "async-channel", "1.8.0" ],
        [ "async-lock", "2.7.0" ],
        [ "async-task", "4.4.0" ],
        [ "atomic-waker", "1.1.0" ],
        [ "fastrand", "1.9.0" ],
        [ "futures-lite", "1.12.0" ]
      ]
    },
    "ciborium": {
      "0.2.0": [
        [ "ciborium-io", "0.2.0" ],
        [ "ciborium-ll", "0.2.0" ],
        [ "serde", "1.0.159" ]
      ]
    },
    "ciborium-ll": {
      "0.2.0": [
        [ "ciborium-io", "0.2.0" ],
        [ "half", "1.8.2" ]
      ]
    },
    "clap": {
      "3.2.23": [
        [ "bitflags", "1.3.2" ],
        [ "clap_lex", "0.2.4" ],
        [ "indexmap", "1.9.3" ],
        [ "textwrap", "0.16.0" ]
      ]
    },
    "clap_lex": {
      "0.2.4": [
        [ "os_str_bytes", "6.5.0" ]
      ]
    },
    "concurrent-queue": {
      "2.1.0": [
        [ "crossbeam-utils", "0.8.15" ]
      ]
    },
    "criterion": {
      "0.4.0": [
        [ "anes", "0.1.6" ],
        [ "approx", "0.5.1" ],
        [ "async-std", "1.12.0" ],
        [ "atty", "0.2.14" ],
        [ "cast", "0.3.0" ],
        [ "ciborium", "0.2.0" ],
        [ "clap", "3.2.23" ],
        [ "criterion-plot", "0.5.0" ],
        [ "csv", "1.2.1" ],
        [ "futures", "0.3.27" ],
        [ "itertools", "0.10.5" ],
        [ "lazy_static", "1.4.0" ],
        [ "num-traits", "0.2.15" ],
        [ "oorandom", "11.1.3" ],
        [ "plotters", "0.3.4" ],
        [ "quickcheck", "1.0.3" ],
        [ "rand", "0.8.5" ],
        [ "rayon", "1.7.0" ],
        [ "regex", "1.7.3" ],
        [ "serde", "1.0.159" ],
        [ "serde_derive", "1.0.159" ],
        [ "serde_json", "1.0.95" ],
        [ "smol", "1.3.0" ],
        [ "tempfile", "3.5.0" ],
        [ "tinytemplate", "1.2.1" ],
        [ "tokio", "1.27.0" ],
        [ "walkdir", "2.3.3" ]
      ]
    },
    "criterion-plot": {
      "0.5.0": [
        [ "cast", "0.3.0" ],
        [ "itertools", "0.10.5" ]
      ]
    },
    "crossbeam-channel": {
      "0.5.7": [
        [ "cfg-if", "1.0.0" ],
        [ "crossbeam-utils", "0.8.15" ]
      ]
    },
    "crossbeam-deque": {
      "0.8.3": [
        [ "cfg-if", "1.0.0" ],
        [ "crossbeam-epoch", "0.9.14" ],
        [ "crossbeam-utils", "0.8.15" ]
      ]
    },
    "crossbeam-epoch": {
      "0.9.14": [
        [ "autocfg", "1.1.0" ],
        [ "cfg-if", "1.0.0" ],
        [ "crossbeam-utils", "0.8.15" ],
        [ "memoffset", "0.8.0" ],
        [ "scopeguard", "1.1.0" ]
      ]
    },
    "crossbeam-utils": {
      "0.8.15": [
        [ "cfg-if", "1.0.0" ]
      ]
    },
    "csv": {
      "1.2.1": [
        [ "csv-core", "0.1.10" ],
        [ "itoa", "1.0.6" ],
        [ "ryu", "1.0.13" ],
        [ "serde", "1.0.159" ]
      ]
    },
    "csv-core": {
      "0.1.10": [
        [ "memchr", "2.5.0" ]
      ]
    },
    "ctor": {
      "0.1.26": [
        [ "quote", "1.0.26" ],
        [ "syn", "1.0.109" ]
      ]
    },
    "errno": {
      "0.3.0": [
        [ "errno-dragonfly", "0.1.2" ],
        [ "libc", "0.2.140" ],
        [ "windows-sys", "0.45.0" ]
      ]
    },
    "errno-dragonfly": {
      "0.1.2": [
        [ "cc", "1.0.79" ],
        [ "libc", "0.2.140" ]
      ]
    },
    "fastrand": {
      "1.9.0": [
        [ "instant", "0.1.12" ]
      ]
    },
    "futures": {
      "0.3.27": [
        [ "futures-channel", "0.3.27" ],
        [ "futures-core", "0.3.27" ],
        [ "futures-executor", "0.3.27" ],
        [ "futures-io", "0.3.27" ],
        [ "futures-sink", "0.3.27" ],
        [ "futures-task", "0.3.27" ],
        [ "futures-util", "0.3.27" ]
      ]
    },
    "futures-channel": {
      "0.3.27": [
        [ "futures-core", "0.3.27" ],
        [ "futures-sink", "0.3.27" ]
      ]
    },
    "futures-executor": {
      "0.3.27": [
        [ "futures-core", "0.3.27" ],
        [ "futures-task", "0.3.27" ],
        [ "futures-util", "0.3.27" ]
      ]
    },
    "futures-lite": {
      "1.12.0": [
        [ "fastrand", "1.9.0" ],
        [ "futures-core", "0.3.27" ],
        [ "futures-io", "0.3.27" ],
        [ "memchr", "2.5.0" ],
        [ "parking", "2.0.0" ],
        [ "pin-project-lite", "0.2.9" ],
        [ "waker-fn", "1.1.0" ]
      ]
    },
    "futures-util": {
      "0.3.27": [
        [ "futures-channel", "0.3.27" ],
        [ "futures-core", "0.3.27" ],
        [ "futures-io", "0.3.27" ],
        [ "futures-sink", "0.3.27" ],
        [ "futures-task", "0.3.27" ],
        [ "memchr", "2.5.0" ],
        [ "pin-project-lite", "0.2.9" ],
        [ "pin-utils", "0.1.0" ],
        [ "slab", "0.4.8" ]
      ]
    },
    "getrandom": {
      "0.2.8": [
        [ "cfg-if", "1.0.0" ],
        [ "libc", "0.2.140" ],
        [ "wasi", "0.11.0+wasi-snapshot-preview1" ]
      ]
    },
    "gloo-timers": {
      "0.2.6": [
        [ "futures-channel", "0.3.27" ],
        [ "futures-core", "0.3.27" ],
        [ "js-sys", "0.3.61" ],
        [ "wasm-bindgen", "0.2.84" ]
      ]
    },
    "hermit-abi": {
      "0.1.19": [
        [ "libc", "0.2.140" ]
      ],
      "0.2.6": [
        [ "libc", "0.2.140" ]
      ]
    },
    "indexmap": {
      "1.9.3": [
        [ "autocfg", "1.1.0" ],
        [ "hashbrown", "0.12.3" ]
      ]
    },
    "instant": {
      "0.1.12": [
        [ "cfg-if", "1.0.0" ]
      ]
    },
    "io-lifetimes": {
      "1.0.9": [
        [ "hermit-abi", "0.3.1" ],
        [ "libc", "0.2.140" ],
        [ "windows-sys", "0.45.0" ]
      ]
    },
    "itertools": {
      "0.10.5": [
        [ "either", "1.8.1" ]
      ]
    },
    "js-sys": {
      "0.3.61": [
        [ "wasm-bindgen", "0.2.84" ]
      ]
    },
    "kv-log-macro": {
      "1.0.7": [
        [ "log", "0.4.17" ]
      ]
    },
    "log": {
      "0.4.17": [
        [ "cfg-if", "1.0.0" ],
        [ "value-bag", "1.0.0-alpha.9" ]
      ]
    },
    "memoffset": {
      "0.8.0": [
        [ "autocfg", "1.1.0" ]
      ]
    },
    "num-traits": {
      "0.2.15": [
        [ "autocfg", "1.1.0" ]
      ]
    },
    "num_cpus": {
      "1.15.0": [
        [ "hermit-abi", "0.2.6" ],
        [ "libc", "0.2.140" ]
      ]
    },
    "plotters": {
      "0.3.4": [
        [ "num-traits", "0.2.15" ],
        [ "plotters-backend", "0.3.4" ],
        [ "plotters-svg", "0.3.3" ],
        [ "wasm-bindgen", "0.2.84" ],
        [ "web-sys", "0.3.61" ]
      ]
    },
    "plotters-svg": {
      "0.3.3": [
        [ "plotters-backend", "0.3.4" ]
      ]
    },
    "polling": {
      "2.6.0": [
        [ "autocfg", "1.1.0" ],
        [ "bitflags", "1.3.2" ],
        [ "cfg-if", "1.0.0" ],
        [ "concurrent-queue", "2.1.0" ],
        [ "libc", "0.2.140" ],
        [ "log", "0.4.17" ],
        [ "pin-project-lite", "0.2.9" ],
        [ "windows-sys", "0.45.0" ]
      ]
    },
    "proc-macro2": {
      "1.0.54": [
        [ "unicode-ident", "1.0.8" ]
      ]
    },
    "quickcheck": {
      "1.0.3": [
        [ "rand", "0.8.5" ]
      ]
    },
    "quote": {
      "1.0.26": [
        [ "proc-macro2", "1.0.54" ]
      ]
    },
    "rand": {
      "0.8.5": [
        [ "libc", "0.2.140" ],
        [ "rand_chacha", "0.3.1" ],
        [ "rand_core", "0.6.4" ]
      ]
    },
    "rand_chacha": {
      "0.3.1": [
        [ "ppv-lite86", "0.2.17" ],
        [ "rand_core", "0.6.4" ]
      ]
    },
    "rand_core": {
      "0.6.4": [
        [ "getrandom", "0.2.8" ]
      ]
    },
    "rayon": {
      "1.7.0": [
        [ "either", "1.8.1" ],
        [ "rayon-core", "1.11.0" ]
      ]
    },
    "rayon-core": {
      "1.11.0": [
        [ "crossbeam-channel", "0.5.7" ],
        [ "crossbeam-deque", "0.8.3" ],
        [ "crossbeam-utils", "0.8.15" ],
        [ "num_cpus", "1.15.0" ]
      ]
    },
    "redox_syscall": {
      "0.3.5": [
        [ "bitflags", "1.3.2" ]
      ]
    },
    "regex": {
      "1.7.3": [
        [ "regex-syntax", "0.6.29" ]
      ]
    },
    "rustix": {
      "0.37.4": [
        [ "bitflags", "1.3.2" ],
        [ "errno", "0.3.0" ],
        [ "io-lifetimes", "1.0.9" ],
        [ "libc", "0.2.140" ],
        [ "linux-raw-sys", "0.3.0" ],
        [ "windows-sys", "0.45.0" ]
      ]
    },
    "same-file": {
      "1.0.6": [
        [ "winapi-util", "0.1.5" ]
      ]
    },
    "serde": {
      "1.0.159": [
        [ "serde_derive", "1.0.159" ]
      ]
    },
    "serde_derive": {
      "1.0.159": [
        [ "proc-macro2", "1.0.54" ],
        [ "quote", "1.0.26" ],
        [ "syn", "2.0.11" ]
      ]
    },
    "serde_json": {
      "1.0.95": [
        [ "itoa", "1.0.6" ],
        [ "ryu", "1.0.13" ],
        [ "serde", "1.0.159" ]
      ]
    },
    "signal-hook": {
      "0.3.15": [
        [ "libc", "0.2.140" ],
        [ "signal-hook-registry", "1.4.1" ]
      ]
    },
    "signal-hook-registry": {
      "1.4.1": [
        [ "libc", "0.2.140" ]
      ]
    },
    "slab": {
      "0.4.8": [
        [ "autocfg", "1.1.0" ]
      ]
    },
    "smol": {
      "1.3.0": [
        [ "async-channel", "1.8.0" ],
        [ "async-executor", "1.5.0" ],
        [ "async-fs", "1.6.0" ],
        [ "async-io", "1.13.0" ],
        [ "async-lock", "2.7.0" ],
        [ "async-net", "1.7.0" ],
        [ "async-process", "1.6.0" ],
        [ "blocking", "1.3.0" ],
        [ "futures-lite", "1.12.0" ]
      ]
    },
    "socket2": {
      "0.4.9": [
        [ "libc", "0.2.140" ],
        [ "winapi", "0.3.9" ]
      ]
    },
    "syn": {
      "1.0.109": [
        [ "proc-macro2", "1.0.54" ],
        [ "quote", "1.0.26" ],
        [ "unicode-ident", "1.0.8" ]
      ],
      "2.0.11": [
        [ "proc-macro2", "1.0.54" ],
        [ "quote", "1.0.26" ],
        [ "unicode-ident", "1.0.8" ]
      ]
    },
    "tempfile": {
      "3.5.0": [
        [ "cfg-if", "1.0.0" ],
        [ "fastrand", "1.9.0" ],
        [ "redox_syscall", "0.3.5" ],
        [ "rustix", "0.37.4" ],
        [ "windows-sys", "0.45.0" ]
      ]
    },
    "tinytemplate": {
      "1.2.1": [
        [ "serde", "1.0.159" ],
        [ "serde_json", "1.0.95" ]
      ]
    },
    "tokio": {
      "1.27.0": [
        [ "autocfg", "1.1.0" ],
        [ "pin-project-lite", "0.2.9" ],
        [ "windows-sys", "0.45.0" ]
      ]
    },
    "value-bag": {
      "1.0.0-alpha.9": [
        [ "ctor", "0.1.26" ],
        [ "version_check", "0.9.4" ]
      ]
    },
    "walkdir": {
      "2.3.3": [
        [ "same-file", "1.0.6" ],
        [ "winapi-util", "0.1.5" ]
      ]
    },
    "wasm-bindgen": {
      "0.2.84": [
        [ "cfg-if", "1.0.0" ],
        [ "wasm-bindgen-macro", "0.2.84" ]
      ]
    },
    "wasm-bindgen-backend": {
      "0.2.84": [
        [ "bumpalo", "3.12.0" ],
        [ "log", "0.4.17" ],
        [ "once_cell", "1.17.1" ],
        [ "proc-macro2", "1.0.54" ],
        [ "quote", "1.0.26" ],
        [ "syn", "1.0.109" ],
        [ "wasm-bindgen-shared", "0.2.84" ]
      ]
    },
    "wasm-bindgen-futures": {
      "0.4.34": [
        [ "cfg-if", "1.0.0" ],
        [ "js-sys", "0.3.61" ],
        [ "wasm-bindgen", "0.2.84" ],
        [ "web-sys", "0.3.61" ]
      ]
    },
    "wasm-bindgen-macro": {
      "0.2.84": [
        [ "quote", "1.0.26" ],
        [ "wasm-bindgen-macro-support", "0.2.84" ]
      ]
    },
    "wasm-bindgen-macro-support": {
      "0.2.84": [
        [ "proc-macro2", "1.0.54" ],
        [ "quote", "1.0.26" ],
        [ "syn", "1.0.109" ],
        [ "wasm-bindgen-backend", "0.2.84" ],
        [ "wasm-bindgen-shared", "0.2.84" ]
      ]
    },
    "web-sys": {
      "0.3.61": [
        [ "js-sys", "0.3.61" ],
        [ "wasm-bindgen", "0.2.84" ]
      ]
    },
    "winapi": {
      "0.3.9": [
        [ "winapi-i686-pc-windows-gnu", "0.4.0" ],
        [ "winapi-x86_64-pc-windows-gnu", "0.4.0" ]
      ]
    },
    "winapi-util": {
      "0.1.5": [
        [ "winapi", "0.3.9" ]
      ]
    },
    "windows-sys": {
      "0.42.0": [
        [ "windows_aarch64_gnullvm", "0.42.2" ],
        [ "windows_aarch64_msvc", "0.42.2" ],
        [ "windows_i686_gnu", "0.42.2" ],
        [ "windows_i686_msvc", "0.42.2" ],
        [ "windows_x86_64_gnu", "0.42.2" ],
        [ "windows_x86_64_gnullvm", "0.42.2" ],
        [ "windows_x86_64_msvc", "0.42.2" ]
      ],
      "0.45.0": [
        [ "windows-targets", "0.42.2" ]
      ]
    },
    "windows-targets": {
      "0.42.2": [
        [ "windows_aarch64_gnullvm", "0.42.2" ],
        [ "windows_aarch64_msvc", "0.42.2" ],
        [ "windows_i686_gnu", "0.42.2" ],
        [ "windows_i686_msvc", "0.42.2" ],
        [ "windows_x86_64_gnu", "0.42.2" ],
        [ "windows_x86_64_gnullvm", "0.42.2" ],
        [ "windows_x86_64_msvc", "0.42.2" ]
      ]
    }
  },
  "sources": {
    "anes": {
      "0.1.6": {
        "hash": "4b46cbb362ab8752921c97e041f5e366ee6297bd428a31275b9fcf1e380f7299",
        "pname": "anes",
        "type": "crates-io",
        "version": "0.1.6"
      }
    },
    "approx": {
      "0.5.1": {
        "hash": "cab112f0a86d568ea0e627cc1d6be74a1e9cd55214684db5561995f6dad897c6",
        "pname": "approx",
        "type": "crates-io",
        "version": "0.5.1"
      }
    },
    "async-channel": {
      "1.8.0": {
        "hash": "cf46fee83e5ccffc220104713af3292ff9bc7c64c7de289f66dae8e38d826833",
        "pname": "async-channel",
        "type": "crates-io",
        "version": "1.8.0"
      }
    },
    "async-executor": {
      "1.5.0": {
        "hash": "17adb73da160dfb475c183343c8cccd80721ea5a605d3eb57125f0a7b7a92d0b",
        "pname": "async-executor",
        "type": "crates-io",
        "version": "1.5.0"
      }
    },
    "async-fs": {
      "1.6.0": {
        "hash": "279cf904654eeebfa37ac9bb1598880884924aab82e290aa65c9e77a0e142e06",
        "pname": "async-fs",
        "type": "crates-io",
        "version": "1.6.0"
      }
    },
    "async-global-executor": {
      "2.3.1": {
        "hash": "f1b6f5d7df27bd294849f8eec66ecfc63d11814df7a4f5d74168a2394467b776",
        "pname": "async-global-executor",
        "type": "crates-io",
        "version": "2.3.1"
      }
    },
    "async-io": {
      "1.13.0": {
        "hash": "0fc5b45d93ef0529756f812ca52e44c221b35341892d3dcc34132ac02f3dd2af",
        "pname": "async-io",
        "type": "crates-io",
        "version": "1.13.0"
      }
    },
    "async-lock": {
      "2.7.0": {
        "hash": "fa24f727524730b077666307f2734b4a1a1c57acb79193127dcc8914d5242dd7",
        "pname": "async-lock",
        "type": "crates-io",
        "version": "2.7.0"
      }
    },
    "async-net": {
      "1.7.0": {
        "hash": "4051e67316bc7eff608fe723df5d32ed639946adcd69e07df41fd42a7b411f1f",
        "pname": "async-net",
        "type": "crates-io",
        "version": "1.7.0"
      }
    },
    "async-process": {
      "1.6.0": {
        "hash": "6381ead98388605d0d9ff86371043b5aa922a3905824244de40dc263a14fcba4",
        "pname": "async-process",
        "type": "crates-io",
        "version": "1.6.0"
      }
    },
    "async-std": {
      "1.12.0": {
        "hash": "62565bb4402e926b29953c785397c6dc0391b7b446e45008b0049eb43cec6f5d",
        "pname": "async-std",
        "type": "crates-io",
        "version": "1.12.0"
      }
    },
    "async-task": {
      "4.4.0": {
        "hash": "ecc7ab41815b3c653ccd2978ec3255c81349336702dfdf62ee6f7069b12a3aae",
        "pname": "async-task",
        "type": "crates-io",
        "version": "4.4.0"
      }
    },
    "atomic-waker": {
      "1.1.0": {
        "hash": "debc29dde2e69f9e47506b525f639ed42300fc014a3e007832592448fa8e4599",
        "pname": "atomic-waker",
        "type": "crates-io",
        "version": "1.1.0"
      }
    },
    "atty": {
      "0.2.14": {
        "hash": "d9b39be18770d11421cdb1b9947a45dd3f37e93092cbf377614828a319d5fee8",
        "pname": "atty",
        "type": "crates-io",
        "version": "0.2.14"
      }
    },
    "autocfg": {
      "1.1.0": {
        "hash": "d468802bab17cbc0cc575e9b053f41e72aa36bfa6b7f55e3529ffa43161b97fa",
        "pname": "autocfg",
        "type": "crates-io",
        "version": "1.1.0"
      }
    },
    "bitflags": {
      "1.3.2": {
        "hash": "bef38d45163c2f1dde094a7dfd33ccf595c92905c8f8f4fdc18d06fb1037718a",
        "pname": "bitflags",
        "type": "crates-io",
        "version": "1.3.2"
      }
    },
    "blocking": {
      "1.3.0": {
        "hash": "3c67b173a56acffd6d2326fb7ab938ba0b00a71480e14902b2591c87bc5741e8",
        "pname": "blocking",
        "type": "crates-io",
        "version": "1.3.0"
      }
    },
    "bumpalo": {
      "3.12.0": {
        "hash": "0d261e256854913907f67ed06efbc3338dfe6179796deefc1ff763fc1aee5535",
        "pname": "bumpalo",
        "type": "crates-io",
        "version": "3.12.0"
      }
    },
    "cast": {
      "0.3.0": {
        "hash": "37b2a672a2cb129a2e41c10b1224bb368f9f37a2b16b612598138befd7b37eb5",
        "pname": "cast",
        "type": "crates-io",
        "version": "0.3.0"
      }
    },
    "cc": {
      "1.0.79": {
        "hash": "50d30906286121d95be3d479533b458f87493b30a4b5f79a607db8f5d11aa91f",
        "pname": "cc",
        "type": "crates-io",
        "version": "1.0.79"
      }
    },
    "cfg-if": {
      "1.0.0": {
        "hash": "baf1de4339761588bc0619e3cbc0120ee582ebb74b53b4efbf79117bd2da40fd",
        "pname": "cfg-if",
        "type": "crates-io",
        "version": "1.0.0"
      }
    },
    "ciborium": {
      "0.2.0": {
        "hash": "b0c137568cc60b904a7724001b35ce2630fd00d5d84805fbb608ab89509d788f",
        "pname": "ciborium",
        "type": "crates-io",
        "version": "0.2.0"
      }
    },
    "ciborium-io": {
      "0.2.0": {
        "hash": "346de753af073cc87b52b2083a506b38ac176a44cfb05497b622e27be899b369",
        "pname": "ciborium-io",
        "type": "crates-io",
        "version": "0.2.0"
      }
    },
    "ciborium-ll": {
      "0.2.0": {
        "hash": "213030a2b5a4e0c0892b6652260cf6ccac84827b83a85a534e178e3906c4cf1b",
        "pname": "ciborium-ll",
        "type": "crates-io",
        "version": "0.2.0"
      }
    },
    "clap": {
      "3.2.23": {
        "hash": "71655c45cb9845d3270c9d6df84ebe72b4dad3c2ba3f7023ad47c144e4e473a5",
        "pname": "clap",
        "type": "crates-io",
        "version": "3.2.23"
      }
    },
    "clap_lex": {
      "0.2.4": {
        "hash": "2850f2f5a82cbf437dd5af4d49848fbdfc27c157c3d010345776f952765261c5",
        "pname": "clap_lex",
        "type": "crates-io",
        "version": "0.2.4"
      }
    },
    "concurrent-queue": {
      "2.1.0": {
        "hash": "c278839b831783b70278b14df4d45e1beb1aad306c07bb796637de9a0e323e8e",
        "pname": "concurrent-queue",
        "type": "crates-io",
        "version": "2.1.0"
      }
    },
    "criterion": {
      "0.4.0": {
        "hash": "e7c76e09c1aae2bc52b3d2f29e13c6572553b30c4aa1b8a49fd70de6412654cb",
        "type": "crates-io"
      }
    },
    "criterion-plot": {
      "0.5.0": {
        "hash": "6b50826342786a51a89e2da3a28f1c32b06e387201bc2d19791f622c673706b1",
        "pname": "criterion-plot",
        "type": "crates-io",
        "version": "0.5.0"
      }
    },
    "crossbeam-channel": {
      "0.5.7": {
        "hash": "cf2b3e8478797446514c91ef04bafcb59faba183e621ad488df88983cc14128c",
        "pname": "crossbeam-channel",
        "type": "crates-io",
        "version": "0.5.7"
      }
    },
    "crossbeam-deque": {
      "0.8.3": {
        "hash": "ce6fd6f855243022dcecf8702fef0c297d4338e226845fe067f6341ad9fa0cef",
        "pname": "crossbeam-deque",
        "type": "crates-io",
        "version": "0.8.3"
      }
    },
    "crossbeam-epoch": {
      "0.9.14": {
        "hash": "46bd5f3f85273295a9d14aedfb86f6aadbff6d8f5295c4a9edb08e819dcf5695",
        "pname": "crossbeam-epoch",
        "type": "crates-io",
        "version": "0.9.14"
      }
    },
    "crossbeam-utils": {
      "0.8.15": {
        "hash": "3c063cd8cc95f5c377ed0d4b49a4b21f632396ff690e8470c29b3359b346984b",
        "pname": "crossbeam-utils",
        "type": "crates-io",
        "version": "0.8.15"
      }
    },
    "csv": {
      "1.2.1": {
        "hash": "0b015497079b9a9d69c02ad25de6c0a6edef051ea6360a327d0bd05802ef64ad",
        "pname": "csv",
        "type": "crates-io",
        "version": "1.2.1"
      }
    },
    "csv-core": {
      "0.1.10": {
        "hash": "2b2466559f260f48ad25fe6317b3c8dac77b5bdb5763ac7d9d6103530663bc90",
        "pname": "csv-core",
        "type": "crates-io",
        "version": "0.1.10"
      }
    },
    "ctor": {
      "0.1.26": {
        "hash": "6d2301688392eb071b0bf1a37be05c469d3cc4dbbd95df672fe28ab021e6a096",
        "pname": "ctor",
        "type": "crates-io",
        "version": "0.1.26"
      }
    },
    "either": {
      "1.8.1": {
        "hash": "7fcaabb2fef8c910e7f4c7ce9f67a1283a1715879a7c230ca9d6d1ae31f16d91",
        "pname": "either",
        "type": "crates-io",
        "version": "1.8.1"
      }
    },
    "errno": {
      "0.3.0": {
        "hash": "50d6a0976c999d473fe89ad888d5a284e55366d9dc9038b1ba2aa15128c4afa0",
        "pname": "errno",
        "type": "crates-io",
        "version": "0.3.0"
      }
    },
    "errno-dragonfly": {
      "0.1.2": {
        "hash": "aa68f1b12764fab894d2755d2518754e71b4fd80ecfb822714a1206c2aab39bf",
        "pname": "errno-dragonfly",
        "type": "crates-io",
        "version": "0.1.2"
      }
    },
    "event-listener": {
      "2.5.3": {
        "hash": "0206175f82b8d6bf6652ff7d71a1e27fd2e4efde587fd368662814d6ec1d9ce0",
        "pname": "event-listener",
        "type": "crates-io",
        "version": "2.5.3"
      }
    },
    "fastrand": {
      "1.9.0": {
        "hash": "e51093e27b0797c359783294ca4f0a911c270184cb10f85783b118614a1501be",
        "pname": "fastrand",
        "type": "crates-io",
        "version": "1.9.0"
      }
    },
    "futures": {
      "0.3.27": {
        "hash": "531ac96c6ff5fd7c62263c5e3c67a603af4fcaee2e1a0ae5565ba3a11e69e549",
        "pname": "futures",
        "type": "crates-io",
        "version": "0.3.27"
      }
    },
    "futures-channel": {
      "0.3.27": {
        "hash": "164713a5a0dcc3e7b4b1ed7d3b433cabc18025386f9339346e8daf15963cf7ac",
        "pname": "futures-channel",
        "type": "crates-io",
        "version": "0.3.27"
      }
    },
    "futures-core": {
      "0.3.27": {
        "hash": "86d7a0c1aa76363dac491de0ee99faf6941128376f1cf96f07db7603b7de69dd",
        "pname": "futures-core",
        "type": "crates-io",
        "version": "0.3.27"
      }
    },
    "futures-executor": {
      "0.3.27": {
        "hash": "1997dd9df74cdac935c76252744c1ed5794fac083242ea4fe77ef3ed60ba0f83",
        "pname": "futures-executor",
        "type": "crates-io",
        "version": "0.3.27"
      }
    },
    "futures-io": {
      "0.3.27": {
        "hash": "89d422fa3cbe3b40dca574ab087abb5bc98258ea57eea3fd6f1fa7162c778b91",
        "pname": "futures-io",
        "type": "crates-io",
        "version": "0.3.27"
      }
    },
    "futures-lite": {
      "1.12.0": {
        "hash": "7694489acd39452c77daa48516b894c153f192c3578d5a839b62c58099fcbf48",
        "pname": "futures-lite",
        "type": "crates-io",
        "version": "1.12.0"
      }
    },
    "futures-sink": {
      "0.3.27": {
        "hash": "ec93083a4aecafb2a80a885c9de1f0ccae9dbd32c2bb54b0c3a65690e0b8d2f2",
        "pname": "futures-sink",
        "type": "crates-io",
        "version": "0.3.27"
      }
    },
    "futures-task": {
      "0.3.27": {
        "hash": "fd65540d33b37b16542a0438c12e6aeead10d4ac5d05bd3f805b8f35ab592879",
        "pname": "futures-task",
        "type": "crates-io",
        "version": "0.3.27"
      }
    },
    "futures-util": {
      "0.3.27": {
        "hash": "3ef6b17e481503ec85211fed8f39d1970f128935ca1f814cd32ac4a6842e84ab",
        "pname": "futures-util",
        "type": "crates-io",
        "version": "0.3.27"
      }
    },
    "getrandom": {
      "0.2.8": {
        "hash": "c05aeb6a22b8f62540c194aac980f2115af067bfe15a0734d7277a768d396b31",
        "pname": "getrandom",
        "type": "crates-io",
        "version": "0.2.8"
      }
    },
    "gloo-timers": {
      "0.2.6": {
        "hash": "9b995a66bb87bebce9a0f4a95aed01daca4872c050bfcb21653361c03bc35e5c",
        "pname": "gloo-timers",
        "type": "crates-io",
        "version": "0.2.6"
      }
    },
    "half": {
      "1.8.2": {
        "hash": "eabb4a44450da02c90444cf74558da904edde8fb4e9035a9a6a4e15445af0bd7",
        "pname": "half",
        "type": "crates-io",
        "version": "1.8.2"
      }
    },
    "hashbrown": {
      "0.12.3": {
        "hash": "8a9ee70c43aaf417c914396645a0fa852624801b24ebb7ae78fe8272889ac888",
        "pname": "hashbrown",
        "type": "crates-io",
        "version": "0.12.3"
      }
    },
    "hermit-abi": {
      "0.1.19": {
        "hash": "62b467343b94ba476dcb2500d242dadbb39557df889310ac77c5d99100aaac33",
        "pname": "hermit-abi",
        "type": "crates-io",
        "version": "0.1.19"
      },
      "0.2.6": {
        "hash": "ee512640fe35acbfb4bb779db6f0d80704c2cacfa2e39b601ef3e3f47d1ae4c7",
        "pname": "hermit-abi",
        "type": "crates-io",
        "version": "0.2.6"
      },
      "0.3.1": {
        "hash": "fed44880c466736ef9a5c5b5facefb5ed0785676d0c02d612db14e54f0d84286",
        "pname": "hermit-abi",
        "type": "crates-io",
        "version": "0.3.1"
      }
    },
    "indexmap": {
      "1.9.3": {
        "hash": "bd070e393353796e801d209ad339e89596eb4c8d430d18ede6a1cced8fafbd99",
        "pname": "indexmap",
        "type": "crates-io",
        "version": "1.9.3"
      }
    },
    "instant": {
      "0.1.12": {
        "hash": "7a5bbe824c507c5da5956355e86a746d82e0e1464f65d862cc5e71da70e94b2c",
        "pname": "instant",
        "type": "crates-io",
        "version": "0.1.12"
      }
    },
    "io-lifetimes": {
      "1.0.9": {
        "hash": "09270fd4fa1111bc614ed2246c7ef56239a3063d5be0d1ec3b589c505d400aeb",
        "pname": "io-lifetimes",
        "type": "crates-io",
        "version": "1.0.9"
      }
    },
    "itertools": {
      "0.10.5": {
        "hash": "b0fd2260e829bddf4cb6ea802289de2f86d6a7a690192fbe91b3f46e0f2c8473",
        "pname": "itertools",
        "type": "crates-io",
        "version": "0.10.5"
      }
    },
    "itoa": {
      "1.0.6": {
        "hash": "453ad9f582a441959e5f0d088b02ce04cfe8d51a8eaf077f12ac6d3e94164ca6",
        "pname": "itoa",
        "type": "crates-io",
        "version": "1.0.6"
      }
    },
    "js-sys": {
      "0.3.61": {
        "hash": "445dde2150c55e483f3d8416706b97ec8e8237c307e5b7b4b8dd15e6af2a0730",
        "pname": "js-sys",
        "type": "crates-io",
        "version": "0.3.61"
      }
    },
    "kv-log-macro": {
      "1.0.7": {
        "hash": "0de8b303297635ad57c9f5059fd9cee7a47f8e8daa09df0fcd07dd39fb22977f",
        "pname": "kv-log-macro",
        "type": "crates-io",
        "version": "1.0.7"
      }
    },
    "lazy_static": {
      "1.4.0": {
        "hash": "e2abad23fbc42b3700f2f279844dc832adb2b2eb069b2df918f455c4e18cc646",
        "pname": "lazy_static",
        "type": "crates-io",
        "version": "1.4.0"
      }
    },
    "libc": {
      "0.2.140": {
        "hash": "99227334921fae1a979cf0bfdfcc6b3e5ce376ef57e16fb6fb3ea2ed6095f80c",
        "pname": "libc",
        "type": "crates-io",
        "version": "0.2.140"
      }
    },
    "linux-raw-sys": {
      "0.3.0": {
        "hash": "cd550e73688e6d578f0ac2119e32b797a327631a42f9433e59d02e139c8df60d",
        "pname": "linux-raw-sys",
        "type": "crates-io",
        "version": "0.3.0"
      }
    },
    "log": {
      "0.4.17": {
        "hash": "abb12e687cfb44aa40f41fc3978ef76448f9b6038cad6aef4259d3c095a2382e",
        "pname": "log",
        "type": "crates-io",
        "version": "0.4.17"
      }
    },
    "memchr": {
      "2.5.0": {
        "hash": "2dffe52ecf27772e601905b7522cb4ef790d2cc203488bbd0e2fe85fcb74566d",
        "pname": "memchr",
        "type": "crates-io",
        "version": "2.5.0"
      }
    },
    "memoffset": {
      "0.8.0": {
        "hash": "d61c719bcfbcf5d62b3a09efa6088de8c54bc0bfcd3ea7ae39fcc186108b8de1",
        "pname": "memoffset",
        "type": "crates-io",
        "version": "0.8.0"
      }
    },
    "num-traits": {
      "0.2.15": {
        "hash": "578ede34cf02f8924ab9447f50c28075b4d3e5b269972345e7e0372b38c6cdcd",
        "pname": "num-traits",
        "type": "crates-io",
        "version": "0.2.15"
      }
    },
    "num_cpus": {
      "1.15.0": {
        "hash": "0fac9e2da13b5eb447a6ce3d392f23a29d8694bff781bf03a16cd9ac8697593b",
        "pname": "num_cpus",
        "type": "crates-io",
        "version": "1.15.0"
      }
    },
    "once_cell": {
      "1.17.1": {
        "hash": "b7e5500299e16ebb147ae15a00a942af264cf3688f47923b8fc2cd5858f23ad3",
        "pname": "once_cell",
        "type": "crates-io",
        "version": "1.17.1"
      }
    },
    "oorandom": {
      "11.1.3": {
        "hash": "0ab1bc2a289d34bd04a330323ac98a1b4bc82c9d9fcb1e66b63caa84da26b575",
        "pname": "oorandom",
        "type": "crates-io",
        "version": "11.1.3"
      }
    },
    "os_str_bytes": {
      "6.5.0": {
        "hash": "ceedf44fb00f2d1984b0bc98102627ce622e083e49a5bacdb3e514fa4238e267",
        "pname": "os_str_bytes",
        "type": "crates-io",
        "version": "6.5.0"
      }
    },
    "parking": {
      "2.0.0": {
        "hash": "427c3892f9e783d91cc128285287e70a59e206ca452770ece88a76f7a3eddd72",
        "pname": "parking",
        "type": "crates-io",
        "version": "2.0.0"
      }
    },
    "pin-project-lite": {
      "0.2.9": {
        "hash": "e0a7ae3ac2f1173085d398531c705756c94a4c56843785df85a60c1a0afac116",
        "pname": "pin-project-lite",
        "type": "crates-io",
        "version": "0.2.9"
      }
    },
    "pin-utils": {
      "0.1.0": {
        "hash": "8b870d8c151b6f2fb93e84a13146138f05d02ed11c7e7c54f8826aaaf7c9f184",
        "pname": "pin-utils",
        "type": "crates-io",
        "version": "0.1.0"
      }
    },
    "plotters": {
      "0.3.4": {
        "hash": "2538b639e642295546c50fcd545198c9d64ee2a38620a628724a3b266d5fbf97",
        "pname": "plotters",
        "type": "crates-io",
        "version": "0.3.4"
      }
    },
    "plotters-backend": {
      "0.3.4": {
        "hash": "193228616381fecdc1224c62e96946dfbc73ff4384fba576e052ff8c1bea8142",
        "pname": "plotters-backend",
        "type": "crates-io",
        "version": "0.3.4"
      }
    },
    "plotters-svg": {
      "0.3.3": {
        "hash": "f9a81d2759aae1dae668f783c308bc5c8ebd191ff4184aaa1b37f65a6ae5a56f",
        "pname": "plotters-svg",
        "type": "crates-io",
        "version": "0.3.3"
      }
    },
    "polling": {
      "2.6.0": {
        "hash": "7e1f879b2998099c2d69ab9605d145d5b661195627eccc680002c4918a7fb6fa",
        "pname": "polling",
        "type": "crates-io",
        "version": "2.6.0"
      }
    },
    "ppv-lite86": {
      "0.2.17": {
        "hash": "5b40af805b3121feab8a3c29f04d8ad262fa8e0561883e7653e024ae4479e6de",
        "pname": "ppv-lite86",
        "type": "crates-io",
        "version": "0.2.17"
      }
    },
    "proc-macro2": {
      "1.0.54": {
        "hash": "e472a104799c74b514a57226160104aa483546de37e839ec50e3c2e41dd87534",
        "pname": "proc-macro2",
        "type": "crates-io",
        "version": "1.0.54"
      }
    },
    "quickcheck": {
      "1.0.3": {
        "hash": "588f6378e4dd99458b60ec275b4477add41ce4fa9f64dcba6f15adccb19b50d6",
        "pname": "quickcheck",
        "type": "crates-io",
        "version": "1.0.3"
      }
    },
    "quote": {
      "1.0.26": {
        "hash": "4424af4bf778aae2051a77b60283332f386554255d722233d09fbfc7e30da2fc",
        "pname": "quote",
        "type": "crates-io",
        "version": "1.0.26"
      }
    },
    "rand": {
      "0.8.5": {
        "hash": "34af8d1a0e25924bc5b7c43c079c942339d8f0a8b57c39049bef581b46327404",
        "pname": "rand",
        "type": "crates-io",
        "version": "0.8.5"
      }
    },
    "rand_chacha": {
      "0.3.1": {
        "hash": "e6c10a63a0fa32252be49d21e7709d4d4baf8d231c2dbce1eaa8141b9b127d88",
        "pname": "rand_chacha",
        "type": "crates-io",
        "version": "0.3.1"
      }
    },
    "rand_core": {
      "0.6.4": {
        "hash": "ec0be4795e2f6a28069bec0b5ff3e2ac9bafc99e6a9a7dc3547996c5c816922c",
        "pname": "rand_core",
        "type": "crates-io",
        "version": "0.6.4"
      }
    },
    "rayon": {
      "1.7.0": {
        "hash": "1d2df5196e37bcc87abebc0053e20787d73847bb33134a69841207dd0a47f03b",
        "pname": "rayon",
        "type": "crates-io",
        "version": "1.7.0"
      }
    },
    "rayon-core": {
      "1.11.0": {
        "hash": "4b8f95bd6966f5c87776639160a66bd8ab9895d9d4ab01ddba9fc60661aebe8d",
        "pname": "rayon-core",
        "type": "crates-io",
        "version": "1.11.0"
      }
    },
    "redox_syscall": {
      "0.3.5": {
        "hash": "567664f262709473930a4bf9e51bf2ebf3348f2e748ccc50dea20646858f8f29",
        "pname": "redox_syscall",
        "type": "crates-io",
        "version": "0.3.5"
      }
    },
    "regex": {
      "1.7.3": {
        "hash": "8b1f693b24f6ac912f4893ef08244d70b6067480d2f1a46e950c9691e6749d1d",
        "pname": "regex",
        "type": "crates-io",
        "version": "1.7.3"
      }
    },
    "regex-syntax": {
      "0.6.29": {
        "hash": "f162c6dd7b008981e4d40210aca20b4bd0f9b60ca9271061b07f78537722f2e1",
        "pname": "regex-syntax",
        "type": "crates-io",
        "version": "0.6.29"
      }
    },
    "rustix": {
      "0.37.4": {
        "hash": "c348b5dc624ecee40108aa2922fed8bad89d7fcc2b9f8cb18f632898ac4a37f9",
        "pname": "rustix",
        "type": "crates-io",
        "version": "0.37.4"
      }
    },
    "ryu": {
      "1.0.13": {
        "hash": "f91339c0467de62360649f8d3e185ca8de4224ff281f66000de5eb2a77a79041",
        "pname": "ryu",
        "type": "crates-io",
        "version": "1.0.13"
      }
    },
    "same-file": {
      "1.0.6": {
        "hash": "93fc1dc3aaa9bfed95e02e6eadabb4baf7e3078b0bd1b4d7b6b0b68378900502",
        "pname": "same-file",
        "type": "crates-io",
        "version": "1.0.6"
      }
    },
    "scopeguard": {
      "1.1.0": {
        "hash": "d29ab0c6d3fc0ee92fe66e2d99f700eab17a8d57d1c1d3b748380fb20baa78cd",
        "pname": "scopeguard",
        "type": "crates-io",
        "version": "1.1.0"
      }
    },
    "serde": {
      "1.0.159": {
        "hash": "3c04e8343c3daeec41f58990b9d77068df31209f2af111e059e9fe9646693065",
        "pname": "serde",
        "type": "crates-io",
        "version": "1.0.159"
      }
    },
    "serde_derive": {
      "1.0.159": {
        "hash": "4c614d17805b093df4b147b51339e7e44bf05ef59fba1e45d83500bcfb4d8585",
        "pname": "serde_derive",
        "type": "crates-io",
        "version": "1.0.159"
      }
    },
    "serde_json": {
      "1.0.95": {
        "hash": "d721eca97ac802aa7777b701877c8004d950fc142651367300d21c1cc0194744",
        "pname": "serde_json",
        "type": "crates-io",
        "version": "1.0.95"
      }
    },
    "signal-hook": {
      "0.3.15": {
        "hash": "732768f1176d21d09e076c23a93123d40bba92d50c4058da34d45c8de8e682b9",
        "pname": "signal-hook",
        "type": "crates-io",
        "version": "0.3.15"
      }
    },
    "signal-hook-registry": {
      "1.4.1": {
        "hash": "d8229b473baa5980ac72ef434c4415e70c4b5e71b423043adb4ba059f89c99a1",
        "pname": "signal-hook-registry",
        "type": "crates-io",
        "version": "1.4.1"
      }
    },
    "slab": {
      "0.4.8": {
        "hash": "6528351c9bc8ab22353f9d776db39a20288e8d6c37ef8cfe3317cf875eecfc2d",
        "pname": "slab",
        "type": "crates-io",
        "version": "0.4.8"
      }
    },
    "smol": {
      "1.3.0": {
        "hash": "13f2b548cd8447f8de0fdf1c592929f70f4fc7039a05e47404b0d096ec6987a1",
        "pname": "smol",
        "type": "crates-io",
        "version": "1.3.0"
      }
    },
    "socket2": {
      "0.4.9": {
        "hash": "64a4a911eed85daf18834cfaa86a79b7d266ff93ff5ba14005426219480ed662",
        "pname": "socket2",
        "type": "crates-io",
        "version": "0.4.9"
      }
    },
    "syn": {
      "1.0.109": {
        "hash": "72b64191b275b66ffe2469e8af2c1cfe3bafa67b529ead792a6d0160888b4237",
        "pname": "syn",
        "type": "crates-io",
        "version": "1.0.109"
      },
      "2.0.11": {
        "hash": "21e3787bb71465627110e7d87ed4faaa36c1f61042ee67badb9e2ef173accc40",
        "pname": "syn",
        "type": "crates-io",
        "version": "2.0.11"
      }
    },
    "tempfile": {
      "3.5.0": {
        "hash": "b9fbec84f381d5795b08656e4912bec604d162bff9291d6189a78f4c8ab87998",
        "pname": "tempfile",
        "type": "crates-io",
        "version": "3.5.0"
      }
    },
    "textwrap": {
      "0.16.0": {
        "hash": "222a222a5bfe1bba4a77b45ec488a741b3cb8872e5e499451fd7d0129c9c7c3d",
        "pname": "textwrap",
        "type": "crates-io",
        "version": "0.16.0"
      }
    },
    "tinytemplate": {
      "1.2.1": {
        "hash": "be4d6b5f19ff7664e8c98d03e2139cb510db9b0a60b55f8e8709b689d939b6bc",
        "pname": "tinytemplate",
        "type": "crates-io",
        "version": "1.2.1"
      }
    },
    "tokio": {
      "1.27.0": {
        "hash": "d0de47a4eecbe11f498978a9b29d792f0d2692d1dd003650c24c76510e3bc001",
        "pname": "tokio",
        "type": "crates-io",
        "version": "1.27.0"
      }
    },
    "unicode-ident": {
      "1.0.8": {
        "hash": "e5464a87b239f13a63a501f2701565754bae92d243d4bb7eb12f6d57d2269bf4",
        "pname": "unicode-ident",
        "type": "crates-io",
        "version": "1.0.8"
      }
    },
    "value-bag": {
      "1.0.0-alpha.9": {
        "hash": "2209b78d1249f7e6f3293657c9779fe31ced465df091bbd433a1cf88e916ec55",
        "pname": "value-bag",
        "type": "crates-io",
        "version": "1.0.0-alpha.9"
      }
    },
    "version_check": {
      "0.9.4": {
        "hash": "49874b5167b65d7193b8aba1567f5c7d93d001cafc34600cee003eda787e483f",
        "pname": "version_check",
        "type": "crates-io",
        "version": "0.9.4"
      }
    },
    "waker-fn": {
      "1.1.0": {
        "hash": "9d5b2c62b4012a3e1eca5a7e077d13b3bf498c4073e33ccd58626607748ceeca",
        "pname": "waker-fn",
        "type": "crates-io",
        "version": "1.1.0"
      }
    },
    "walkdir": {
      "2.3.3": {
        "hash": "36df944cda56c7d8d8b7496af378e6b16de9284591917d307c9b4d313c44e698",
        "pname": "walkdir",
        "type": "crates-io",
        "version": "2.3.3"
      }
    },
    "wasi": {
      "0.11.0+wasi-snapshot-preview1": {
        "hash": "9c8d87e72b64a3b4db28d11ce29237c246188f4f51057d65a7eab63b7987e423",
        "pname": "wasi",
        "type": "crates-io",
        "version": "0.11.0+wasi-snapshot-preview1"
      }
    },
    "wasm-bindgen": {
      "0.2.84": {
        "hash": "31f8dcbc21f30d9b8f2ea926ecb58f6b91192c17e9d33594b3df58b2007ca53b",
        "pname": "wasm-bindgen",
        "type": "crates-io",
        "version": "0.2.84"
      }
    },
    "wasm-bindgen-backend": {
      "0.2.84": {
        "hash": "95ce90fd5bcc06af55a641a86428ee4229e44e07033963a2290a8e241607ccb9",
        "pname": "wasm-bindgen-backend",
        "type": "crates-io",
        "version": "0.2.84"
      }
    },
    "wasm-bindgen-futures": {
      "0.4.34": {
        "hash": "f219e0d211ba40266969f6dbdd90636da12f75bee4fc9d6c23d1260dadb51454",
        "pname": "wasm-bindgen-futures",
        "type": "crates-io",
        "version": "0.4.34"
      }
    },
    "wasm-bindgen-macro": {
      "0.2.84": {
        "hash": "4c21f77c0bedc37fd5dc21f897894a5ca01e7bb159884559461862ae90c0b4c5",
        "pname": "wasm-bindgen-macro",
        "type": "crates-io",
        "version": "0.2.84"
      }
    },
    "wasm-bindgen-macro-support": {
      "0.2.84": {
        "hash": "2aff81306fcac3c7515ad4e177f521b5c9a15f2b08f4e32d823066102f35a5f6",
        "pname": "wasm-bindgen-macro-support",
        "type": "crates-io",
        "version": "0.2.84"
      }
    },
    "wasm-bindgen-shared": {
      "0.2.84": {
        "hash": "0046fef7e28c3804e5e38bfa31ea2a0f73905319b677e57ebe37e49358989b5d",
        "pname": "wasm-bindgen-shared",
        "type": "crates-io",
        "version": "0.2.84"
      }
    },
    "web-sys": {
      "0.3.61": {
        "hash": "e33b99f4b23ba3eec1a53ac264e35a755f00e966e0065077d6027c0f575b0b97",
        "pname": "web-sys",
        "type": "crates-io",
        "version": "0.3.61"
      }
    },
    "winapi": {
      "0.3.9": {
        "hash": "5c839a674fcd7a98952e593242ea400abe93992746761e38641405d28b00f419",
        "pname": "winapi",
        "type": "crates-io",
        "version": "0.3.9"
      }
    },
    "winapi-i686-pc-windows-gnu": {
      "0.4.0": {
        "hash": "ac3b87c63620426dd9b991e5ce0329eff545bccbbb34f3be09ff6fb6ab51b7b6",
        "pname": "winapi-i686-pc-windows-gnu",
        "type": "crates-io",
        "version": "0.4.0"
      }
    },
    "winapi-util": {
      "0.1.5": {
        "hash": "70ec6ce85bb158151cae5e5c87f95a8e97d2c0c4b001223f33a334e3ce5de178",
        "pname": "winapi-util",
        "type": "crates-io",
        "version": "0.1.5"
      }
    },
    "winapi-x86_64-pc-windows-gnu": {
      "0.4.0": {
        "hash": "712e227841d057c1ee1cd2fb22fa7e5a5461ae8e48fa2ca79ec42cfc1931183f",
        "pname": "winapi-x86_64-pc-windows-gnu",
        "type": "crates-io",
        "version": "0.4.0"
      }
    },
    "windows-sys": {
      "0.42.0": {
        "hash": "5a3e1820f08b8513f676f7ab6c1f99ff312fb97b553d30ff4dd86f9f15728aa7",
        "pname": "windows-sys",
        "type": "crates-io",
        "version": "0.42.0"
      },
      "0.45.0": {
        "hash": "75283be5efb2831d37ea142365f009c02ec203cd29a3ebecbc093d52315b66d0",
        "pname": "windows-sys",
        "type": "crates-io",
        "version": "0.45.0"
      }
    },
    "windows-targets": {
      "0.42.2": {
        "hash": "8e5180c00cd44c9b1c88adb3693291f1cd93605ded80c250a75d472756b4d071",
        "pname": "windows-targets",
        "type": "crates-io",
        "version": "0.42.2"
      }
    },
    "windows_aarch64_gnullvm": {
      "0.42.2": {
        "hash": "597a5118570b68bc08d8d59125332c54f1ba9d9adeedeef5b99b02ba2b0698f8",
        "pname": "windows_aarch64_gnullvm",
        "type": "crates-io",
        "version": "0.42.2"
      }
    },
    "windows_aarch64_msvc": {
      "0.42.2": {
        "hash": "e08e8864a60f06ef0d0ff4ba04124db8b0fb3be5776a5cd47641e942e58c4d43",
        "pname": "windows_aarch64_msvc",
        "type": "crates-io",
        "version": "0.42.2"
      }
    },
    "windows_i686_gnu": {
      "0.42.2": {
        "hash": "c61d927d8da41da96a81f029489353e68739737d3beca43145c8afec9a31a84f",
        "pname": "windows_i686_gnu",
        "type": "crates-io",
        "version": "0.42.2"
      }
    },
    "windows_i686_msvc": {
      "0.42.2": {
        "hash": "44d840b6ec649f480a41c8d80f9c65108b92d89345dd94027bfe06ac444d1060",
        "pname": "windows_i686_msvc",
        "type": "crates-io",
        "version": "0.42.2"
      }
    },
    "windows_x86_64_gnu": {
      "0.42.2": {
        "hash": "8de912b8b8feb55c064867cf047dda097f92d51efad5b491dfb98f6bbb70cb36",
        "pname": "windows_x86_64_gnu",
        "type": "crates-io",
        "version": "0.42.2"
      }
    },
    "windows_x86_64_gnullvm": {
      "0.42.2": {
        "hash": "26d41b46a36d453748aedef1486d5c7a85db22e56aff34643984ea85514e94a3",
        "pname": "windows_x86_64_gnullvm",
        "type": "crates-io",
        "version": "0.42.2"
      }
    },
    "windows_x86_64_msvc": {
      "0.42.2": {
        "hash": "9aec5da331524158c6d1a4ac0ab1541149c0b9505fde06423b02f5ef0106b9f0",
        "pname": "windows_x86_64_msvc",
        "type": "crates-io",
        "version": "0.42.2"
      }
    }
  }
}
