{
  "_generic": {
    "defaultPackage": "proc-macro2",
    "location": "",
    "packages": {
      "proc-macro2": "1.0.53"
    },
    "sourcesAggregatedHash": null,
    "subsystem": "rust"
  },
  "_subsystem": {
    "gitSources": [],
    "meta": {
      "proc-macro2": {
        "1.0.53": {
          "description": "A substitute implementation of the compiler's `proc_macro` API to decouple token-based libraries from the procedural macro use case.", "license": [   "mit",   "asl20"
          ]
        }
      }
    },
    "relPathReplacements": {
      "proc-macro2": {
        "1.0.53": {}
      }
    }
  },
  "cyclicDependencies": {},
  "dependencies": {
    "proc-macro2": {
      "1.0.53": [
        [ "quote", "1.0.26" ],
        [ "rustversion", "1.0.12" ],
        [ "unicode-ident", "1.0.8" ]
      ],
      "1.0.53$crates-io": [
        [ "unicode-ident", "1.0.8" ]
      ]
    },
    "quote": {
      "1.0.26": [
        [ "proc-macro2", "1.0.53$crates-io" ]
      ]
    }
  },
  "sources": {
    "proc-macro2": {
      "1.0.53": {
        "hash": "ba466839c78239c09faf015484e5cc04860f88242cff4d03eb038f04b4699b73",
        "type": "crates-io"
      },
      "1.0.53$crates-io": {
        "hash": "ba466839c78239c09faf015484e5cc04860f88242cff4d03eb038f04b4699b73",
        "pname": "proc-macro2",
        "type": "crates-io",
        "version": "1.0.53"
      }
    },
    "quote": {
      "1.0.26": {
        "hash": "4424af4bf778aae2051a77b60283332f386554255d722233d09fbfc7e30da2fc",
        "pname": "quote",
        "type": "crates-io",
        "version": "1.0.26"
      }
    },
    "rustversion": {
      "1.0.12": {
        "hash": "4f3208ce4d8448b3f3e7d168a73f5e0c43a61e32930de3bceeccedb388b6bf06",
        "pname": "rustversion",
        "type": "crates-io",
        "version": "1.0.12"
      }
    },
    "unicode-ident": {
      "1.0.8": {
        "hash": "e5464a87b239f13a63a501f2701565754bae92d243d4bb7eb12f6d57d2269bf4",
        "pname": "unicode-ident",
        "type": "crates-io",
        "version": "1.0.8"
      }
    }
  }
}
