{
  "_generic": {
    "defaultPackage": "data-accessor",
    "location": "",
    "packages": {
      "data-accessor": "0.2.3.1"
    },
    "sourcesAggregatedHash": null,
    "subsystem": "haskell"
  },
  "_subsystem": {
    "cabalHashes": {},
    "compiler": {
      "name": "ghc",
      "version": "9.0.2"
    }
  },
  "cyclicDependencies": {},
  "dependencies": {},
  "sources": {
    "data-accessor": {
      "0.2.3.1": {
        "hash": "sha256:06a3c790a27e107aaa4d11556866e874d1e4edc814bd4928bc6ff61f3b0d5791",
        "type": "http",
        "url": "https://hackage.haskell.org/package/data-accessor-0.2.3.1/data-accessor-0.2.3.1.tar.gz"
      }
    }
  }
}
