{
  "_generic": {
    "defaultPackage": "encoding_rs",
    "location": "",
    "packages": {
      "encoding_rs": "0.8.32"
    },
    "sourcesAggregatedHash": null,
    "subsystem": "rust"
  },
  "_subsystem": {
    "gitSources": [],
    "meta": {
      "encoding_rs": {
        "0.8.32": {
          "description": "A Gecko-oriented implementation of the Encoding Standard", "homepage": "https://docs.rs/encoding_rs/", "license": [   "asl20"
          ]
        }
      }
    },
    "relPathReplacements": {
      "encoding_rs": {
        "0.8.32": {}
      }
    }
  },
  "cyclicDependencies": {},
  "dependencies": {
    "bincode": {
      "1.3.3": [
        [ "serde", "1.0.163" ]
      ]
    },
    "encoding_rs": {
      "0.8.32": [
        [ "bincode", "1.3.3" ],
        [ "cfg-if", "1.0.0" ],
        [ "packed_simd_2", "0.3.8" ],
        [ "serde", "1.0.163" ],
        [ "serde_derive", "1.0.163" ],
        [ "serde_json", "1.0.96" ]
      ]
    },
    "packed_simd_2": {
      "0.3.8": [
        [ "cfg-if", "1.0.0" ],
        [ "libm", "0.1.4" ]
      ]
    },
    "proc-macro2": {
      "1.0.56": [
        [ "unicode-ident", "1.0.8" ]
      ]
    },
    "quote": {
      "1.0.27": [
        [ "proc-macro2", "1.0.56" ]
      ]
    },
    "serde_derive": {
      "1.0.163": [
        [ "proc-macro2", "1.0.56" ],
        [ "quote", "1.0.27" ],
        [ "syn", "2.0.16" ]
      ]
    },
    "serde_json": {
      "1.0.96": [
        [ "itoa", "1.0.6" ],
        [ "ryu", "1.0.13" ],
        [ "serde", "1.0.163" ]
      ]
    },
    "syn": {
      "2.0.16": [
        [ "proc-macro2", "1.0.56" ],
        [ "quote", "1.0.27" ],
        [ "unicode-ident", "1.0.8" ]
      ]
    }
  },
  "sources": {
    "bincode": {
      "1.3.3": {
        "hash": "b1f45e9417d87227c7a56d22e471c6206462cba514c7590c09aff4cf6d1ddcad",
        "pname": "bincode",
        "type": "crates-io",
        "version": "1.3.3"
      }
    },
    "cfg-if": {
      "1.0.0": {
        "hash": "baf1de4339761588bc0619e3cbc0120ee582ebb74b53b4efbf79117bd2da40fd",
        "pname": "cfg-if",
        "type": "crates-io",
        "version": "1.0.0"
      }
    },
    "encoding_rs": {
      "0.8.32": {
        "hash": "071a31f4ee85403370b58aca746f01041ede6f0da2730960ad001edc2b71b394",
        "type": "crates-io"
      }
    },
    "itoa": {
      "1.0.6": {
        "hash": "453ad9f582a441959e5f0d088b02ce04cfe8d51a8eaf077f12ac6d3e94164ca6",
        "pname": "itoa",
        "type": "crates-io",
        "version": "1.0.6"
      }
    },
    "libm": {
      "0.1.4": {
        "hash": "7fc7aa29613bd6a620df431842069224d8bc9011086b1db4c0e0cd47fa03ec9a",
        "pname": "libm",
        "type": "crates-io",
        "version": "0.1.4"
      }
    },
    "packed_simd_2": {
      "0.3.8": {
        "hash": "a1914cd452d8fccd6f9db48147b29fd4ae05bea9dc5d9ad578509f72415de282",
        "pname": "packed_simd_2",
        "type": "crates-io",
        "version": "0.3.8"
      }
    },
    "proc-macro2": {
      "1.0.56": {
        "hash": "2b63bdb0cd06f1f4dedf69b254734f9b45af66e4a031e42a7480257d9898b435",
        "pname": "proc-macro2",
        "type": "crates-io",
        "version": "1.0.56"
      }
    },
    "quote": {
      "1.0.27": {
        "hash": "8f4f29d145265ec1c483c7c654450edde0bfe043d3938d6972630663356d9500",
        "pname": "quote",
        "type": "crates-io",
        "version": "1.0.27"
      }
    },
    "ryu": {
      "1.0.13": {
        "hash": "f91339c0467de62360649f8d3e185ca8de4224ff281f66000de5eb2a77a79041",
        "pname": "ryu",
        "type": "crates-io",
        "version": "1.0.13"
      }
    },
    "serde": {
      "1.0.163": {
        "hash": "2113ab51b87a539ae008b5c6c02dc020ffa39afd2d83cffcb3f4eb2722cebec2",
        "pname": "serde",
        "type": "crates-io",
        "version": "1.0.163"
      }
    },
    "serde_derive": {
      "1.0.163": {
        "hash": "8c805777e3930c8883389c602315a24224bcc738b63905ef87cd1420353ea93e",
        "pname": "serde_derive",
        "type": "crates-io",
        "version": "1.0.163"
      }
    },
    "serde_json": {
      "1.0.96": {
        "hash": "057d394a50403bcac12672b2b18fb387ab6d289d957dab67dd201875391e52f1",
        "pname": "serde_json",
        "type": "crates-io",
        "version": "1.0.96"
      }
    },
    "syn": {
      "2.0.16": {
        "hash": "a6f671d4b5ffdb8eadec19c0ae67fe2639df8684bd7bc4b83d986b8db549cf01",
        "pname": "syn",
        "type": "crates-io",
        "version": "2.0.16"
      }
    },
    "unicode-ident": {
      "1.0.8": {
        "hash": "e5464a87b239f13a63a501f2701565754bae92d243d4bb7eb12f6d57d2269bf4",
        "pname": "unicode-ident",
        "type": "crates-io",
        "version": "1.0.8"
      }
    }
  }
}
