{
  "_generic": {
    "defaultPackage": "@types/react-router-dom",
    "location": "",
    "packages": {
      "@types/react-router-dom": "5.3.3"
    },
    "sourcesAggregatedHash": null,
    "subsystem": "nodejs"
  },
  "_subsystem": {
    "meta": {
      "license": []
    },
    "nodejsVersion": "14"
  },
  "cyclicDependencies": {},
  "dependencies": {
    "@types/react": {
      "18.0.33": [
        [ "@types/prop-types", "15.7.5" ],
        [ "@types/scheduler", "0.16.3" ],
        [ "csstype", "3.1.2" ]
      ]
    },
    "@types/react-router": {
      "5.1.20": [
        [ "@types/history", "4.7.11" ],
        [ "@types/react", "18.0.33" ]
      ]
    },
    "@types/react-router-dom": {
      "5.3.3": [
        [ "@types/history", "4.7.11" ],
        [ "@types/react", "18.0.33" ],
        [ "@types/react-router", "5.1.20" ]
      ],
      "unknown": [
        [ "@types/history", "4.7.11" ],
        [ "@types/prop-types", "15.7.5" ],
        [ "@types/react", "18.0.33" ],
        [ "@types/react-router", "5.1.20" ],
        [ "@types/react-router-dom", "5.3.3" ],
        [ "@types/scheduler", "0.16.3" ],
        [ "csstype", "3.1.2" ]
      ]
    }
  },
  "sources": {
    "@types/history": {
      "4.7.11": {
        "hash": "sha512-qjDJRrmvBMiTx+jyLxvLfJU7UznFuokDv4f3WRuriHKERccVpFU+8XMQUAbDzoiJCsmexxRExQeMwwCdamSKDA==",
        "type": "http",
        "url": "https://registry.npmjs.org/@types/history/-/history-4.7.11.tgz"
      }
    },
    "@types/prop-types": {
      "15.7.5": {
        "hash": "sha512-JCB8C6SnDoQf0cNycqd/35A7MjcnK+ZTqE7judS6o7utxUCg6imJg3QK2qzHKszlTjcj2cn+NwMB2i96ubpj7w==",
        "type": "http",
        "url": "https://registry.npmjs.org/@types/prop-types/-/prop-types-15.7.5.tgz"
      }
    },
    "@types/react": {
      "18.0.33": {
        "hash": "sha512-sHxzVxeanvQyQ1lr8NSHaj0kDzcNiGpILEVt69g9S31/7PfMvNCKLKcsHw4lYKjs3cGNJjXSP4mYzX43QlnjNA==",
        "type": "http",
        "url": "https://registry.npmjs.org/@types/react/-/react-18.0.33.tgz"
      }
    },
    "@types/react-router": {
      "5.1.20": {
        "hash": "sha512-jGjmu/ZqS7FjSH6owMcD5qpq19+1RS9DeVRqfl1FeBMxTDQAGwlMWOcs52NDoXaNKyG3d1cYQFMs9rCrb88o9Q==",
        "type": "http",
        "url": "https://registry.npmjs.org/@types/react-router/-/react-router-5.1.20.tgz"
      }
    },
    "@types/react-router-dom": {
      "5.3.3": {
        "hash": "sha512-kpqnYK4wcdm5UaWI3fLcELopqLrHgLqNsdpHauzlQktfkHL3npOSwtj1Uz9oKBAzs7lFtVkV8j83voAz2D8fhw==",
        "type": "http",
        "url": "https://registry.npmjs.org/@types/react-router-dom/-/react-router-dom-5.3.3.tgz"
      }
    },
    "@types/scheduler": {
      "0.16.3": {
        "hash": "sha512-5cJ8CB4yAx7BH1oMvdU0Jh9lrEXyPkar6F9G/ERswkCuvP4KQZfZkSjcMbAICCpQTN4OuZn8tz0HiKv9TGZgrQ==",
        "type": "http",
        "url": "https://registry.npmjs.org/@types/scheduler/-/scheduler-0.16.3.tgz"
      }
    },
    "csstype": {
      "3.1.2": {
        "hash": "sha512-I7K1Uu0MBPzaFKg4nI5Q7Vs2t+3gWWW648spaF+Rg7pI9ds18Ugn+lvg4SHczUdKlHI5LWBXyqfS8+DufyBsgQ==",
        "type": "http",
        "url": "https://registry.npmjs.org/csstype/-/csstype-3.1.2.tgz"
      }
    }
  }
}
