{
  "_generic": {
    "defaultPackage": "percent-encoding",
    "location": "",
    "packages": {
      "percent-encoding": "2.3.0"
    },
    "sourcesAggregatedHash": null,
    "subsystem": "rust"
  },
  "_subsystem": {
    "gitSources": [],
    "meta": {
      "percent-encoding": {
        "2.3.0": {
          "description": "Percent encoding and decoding", "license": [   "mit",   "asl20"
          ]
        }
      }
    },
    "relPathReplacements": {
      "percent-encoding": {
        "2.3.0": {}
      }
    }
  },
  "cyclicDependencies": {},
  "dependencies": {},
  "sources": {
    "percent-encoding": {
      "2.3.0": {
        "hash": "9b2a4787296e9989611394c33f193f676704af1686e70b8f8033ab5ba9a35a94",
        "type": "crates-io"
      }
    }
  }
}
