{
  "_generic": {
    "defaultPackage": "iovec",
    "location": "",
    "packages": {
      "iovec": "0.1.4"
    },
    "sourcesAggregatedHash": null,
    "subsystem": "rust"
  },
  "_subsystem": {
    "gitSources": [],
    "meta": {
      "iovec": {
        "0.1.4": {
          "description": "Portable buffer type for scatter/gather I/O operations\n", "homepage": "https://github.com/carllerche/iovec", "license": []
        }
      }
    },
    "relPathReplacements": {
      "iovec": {
        "0.1.4": {}
      }
    }
  },
  "cyclicDependencies": {},
  "dependencies": {
    "iovec": {
      "0.1.4": [
        [ "libc", "0.2.144" ]
      ]
    }
  },
  "sources": {
    "iovec": {
      "0.1.4": {
        "hash": "b2b3ea6ff95e175473f8ffe6a7eb7c00d054240321b84c57051175fe3c1e075e",
        "type": "crates-io"
      }
    },
    "libc": {
      "0.2.144": {
        "hash": "2b00cc1c228a6782d0f076e7b232802e0c5689d41bb5df366f2a6b6621cfdfe1",
        "pname": "libc",
        "type": "crates-io",
        "version": "0.2.144"
      }
    }
  }
}
