{
  "_generic": {
    "defaultPackage": "radium",
    "location": "",
    "packages": {
      "radium": "1.0.0"
    },
    "sourcesAggregatedHash": null,
    "subsystem": "rust"
  },
  "_subsystem": {
    "gitSources": [],
    "meta": {
      "radium": {
        "1.0.0": {
          "description": "Portable interfaces for maybe-atomic types", "homepage": "https://ferrilab.github.io/ferrilab", "license": [   "mit"
          ]
        }
      }
    },
    "relPathReplacements": {
      "radium": {
        "1.0.0": {}
      }
    }
  },
  "cyclicDependencies": {},
  "dependencies": {
    "radium": {
      "1.0.0": [
        [ "static_assertions", "1.1.0" ]
      ]
    }
  },
  "sources": {
    "radium": {
      "1.0.0": {
        "hash": "9105a0eb829980504f26f14e3a45e8ea774577628bb05a99876fcb2502c2718e",
        "type": "crates-io"
      }
    },
    "static_assertions": {
      "1.1.0": {
        "hash": "a2eb9349b6444b326872e140eb1cf5e7c522154d69e7a0ffb0fb81c06b37543f",
        "type": "crates-io"
      }
    }
  }
}
