{
  "_generic": {
    "defaultPackage": "@types/fs-extra",
    "location": "",
    "packages": {
      "@types/fs-extra": "9.0.13"
    },
    "sourcesAggregatedHash": null,
    "subsystem": "nodejs"
  },
  "_subsystem": {
    "meta": {
      "license": []
    },
    "nodejsVersion": "14"
  },
  "cyclicDependencies": {},
  "dependencies": {
    "@types/fs-extra": {
      "9.0.13": [
        [ "@types/node", "18.11.15" ]
      ],
      "unknown": [
        [ "@types/fs-extra", "9.0.13" ]
      ]
    }
  },
  "sources": {
    "@types/fs-extra": {
      "9.0.13": {
        "hash": "sha512-nEnwB++1u5lVDM2UI4c1+5R+FYaKfaAzS4OococimjVm3nQw3TuzH5UNsocrcTBbhnerblyHj4A49qXbIiZdpA==",
        "type": "http",
        "url": "https://registry.npmjs.org/@types/fs-extra/-/fs-extra-9.0.13.tgz"
      }
    },
    "@types/node": {
      "18.11.15": {
        "hash": "sha512-VkhBbVo2+2oozlkdHXLrb3zjsRkpdnaU2bXmX8Wgle3PUi569eLRaHGlgETQHR7lLL1w7GiG3h9SnePhxNDecw==",
        "type": "http",
        "url": "https://registry.npmjs.org/@types/node/-/node-18.11.15.tgz"
      }
    }
  }
}
