{
  "_generic": {
    "defaultPackage": "num_threads",
    "location": "",
    "packages": {
      "num_threads": "0.1.6"
    },
    "sourcesAggregatedHash": null,
    "subsystem": "rust"
  },
  "_subsystem": {
    "gitSources": [],
    "meta": {
      "num_threads": {
        "0.1.6": {
          "description": "A minimal library that determines the number of running threads for the current process.", "license": [   "mit",   "asl20"
          ]
        }
      }
    },
    "relPathReplacements": {
      "num_threads": {
        "0.1.6": {}
      }
    }
  },
  "cyclicDependencies": {},
  "dependencies": {
    "num_threads": {
      "0.1.6": [
        [ "libc", "0.2.145" ]
      ]
    }
  },
  "sources": {
    "libc": {
      "0.2.145": {
        "hash": "fc86cde3ff845662b8f4ef6cb50ea0e20c524eb3d29ae048287e06a1b3fa6a81",
        "pname": "libc",
        "type": "crates-io",
        "version": "0.2.145"
      }
    },
    "num_threads": {
      "0.1.6": {
        "hash": "2819ce041d2ee131036f4fc9d6ae7ae125a3a40e97ba64d04fe799ad9dabbb44",
        "type": "crates-io"
      }
    }
  }
}
